InterestCalcApp/__init__.py
InterestCalcApp-0.3.dist-info/LICENSE.txt
InterestCalcApp-0.3.dist-info/METADATA
InterestCalcApp-0.3.dist-info/WHEEL
InterestCalcApp-0.3.dist-info/top_level.txt
InterestCalcApp-0.3.dist-info/RECORD
