Metadata-Version: 2.1
Name: InterestCalcApp
Version: 0.3
Summary: Interest calculating as a part of study
Author: Sandeep Sathya
Author-email: sandeepsathyan1996@gmail.com
Classifier: Programming Language :: Python :: 3
Classifier: License :: OSI Approved :: MIT License
Classifier: Operating System :: OS Independent
License-File: LICENSE.txt
